linuxprivchecker/__init__.py
linuxprivchecker/__main__.py
linuxprivchecker-1.0.0.dist-info/LICENSE
linuxprivchecker-1.0.0.dist-info/METADATA
linuxprivchecker-1.0.0.dist-info/WHEEL
linuxprivchecker-1.0.0.dist-info/entry_points.txt
linuxprivchecker-1.0.0.dist-info/top_level.txt
linuxprivchecker-1.0.0.dist-info/RECORD
