Metadata-Version: 2.1
Name: linuxprivchecker
Version: 1.0.0
Summary: Linux Privilege Escalation Check Script
Home-page: https://github.com/sleventyeleven/linuxprivchecker
Author: Michael "Sleventyeleven" Contino
Author-email: mcontino@live.com
License: UNKNOWN
Platform: UNKNOWN
Classifier: Programming Language :: Python :: 3
Classifier: License :: OSI Approved :: MIT License
Classifier: Operating System :: POSIX :: Linux
Requires-Python: >=3
